poetry_plugin_pycopy/__init__.py
poetry_plugin_pycopy/models.py
poetry_plugin_pycopy/plugin.py
poetry_plugin_pycopy/pycopy.py
poetry_plugin_pycopy-1.0.6.dist-info/entry_points.txt
poetry_plugin_pycopy-1.0.6.dist-info/WHEEL
poetry_plugin_pycopy-1.0.6.dist-info/METADATA
poetry_plugin_pycopy-1.0.6.dist-info/RECORD
