Metadata-Version: 2.1
Name: poetry-plugin-pycopy
Version: 1.0.6
Summary: Copy fields from pyproject.toml to source directory
License: unlicense.org
Author: Daniel Fajt
Author-email: daniel29se@gmail.com
Requires-Python: >=3.7,<4.0
Classifier: License :: OSI Approved :: The Unlicense (Unlicense)
Classifier: License :: Other/Proprietary License
Classifier: Operating System :: OS Independent
Classifier: Programming Language :: Python :: 3
Classifier: Programming Language :: Python :: 3.7
Classifier: Programming Language :: Python :: 3.8
Classifier: Programming Language :: Python :: 3.9
Classifier: Programming Language :: Python :: 3.10
Classifier: Programming Language :: Python :: 3.11
Classifier: Programming Language :: Python :: 3
Requires-Dist: poetry (>=1.2.2,<2.0.0)
